cli/__init__.py
foresight_model_cli-17.8.1.dist-info/DESCRIPTION.rst
foresight_model_cli-17.8.1.dist-info/METADATA
foresight_model_cli-17.8.1.dist-info/RECORD
foresight_model_cli-17.8.1.dist-info/WHEEL
foresight_model_cli-17.8.1.dist-info/entry_points.txt
foresight_model_cli-17.8.1.dist-info/metadata.json
foresight_model_cli-17.8.1.dist-info/top_level.txt
