Metadata-Version: 2.0
Name: foresight-model-cli
Version: 17.8.1
Summary: Foresight CLI
Home-page: UNKNOWN
Author: Fouad Omri
Author-email: fouad.omri@qio.io
License: UNKNOWN
Platform: UNKNOWN
Requires-Dist: fire (==0.1.1)
Requires-Dist: futures (==3.1.1)
Requires-Dist: jinja2 (==2.9.6)
Requires-Dist: kubernetes (==3.0.0a1)
Requires-Dist: pyyaml (==3.12)
Requires-Dist: requests (==2.18.1)
Requires-Dist: tabulate (==0.7.7)
